Calcom/__init__.py
Calcom/calcom.py
Calcom-1.0.2.dist-info/LICENSE
Calcom-1.0.2.dist-info/METADATA
Calcom-1.0.2.dist-info/WHEEL
Calcom-1.0.2.dist-info/top_level.txt
Calcom-1.0.2.dist-info/RECORD
